README.rst
setup.cfg
setup.py
mailhole/__init__.py
mailhole/mailhole.py
mailhole.egg-info/PKG-INFO
mailhole.egg-info/SOURCES.txt
mailhole.egg-info/dependency_links.txt
mailhole.egg-info/entry_points.txt
mailhole.egg-info/top_level.txt