Metadata-Version: 1.0
Name: mailhole
Version: 0.0.1
Summary: A simple application to test email sending functionality
Home-page: https://github.com/Ch00k/mailhole
Author: Andriy Yurchuk
Author-email: ayurchuk@minuteware.net
License: LICENSE.txt
Platform: UNKNOWN
